schemainspect/__init__.py
schemainspect/get.py
schemainspect/inspected.py
schemainspect/inspector.py
schemainspect/misc.py
schemainspect/pg/__init__.py
schemainspect/pg/obj.py
schemainspect/pg/sql/collations.sql
schemainspect/pg/sql/collations9.sql
schemainspect/pg/sql/column-privileges.sql
schemainspect/pg/sql/constraints.sql
schemainspect/pg/sql/deps.sql
schemainspect/pg/sql/domains.sql
schemainspect/pg/sql/enums.sql
schemainspect/pg/sql/extensions.sql
schemainspect/pg/sql/functions.sql
schemainspect/pg/sql/indexes.sql
schemainspect/pg/sql/memberships.sql
schemainspect/pg/sql/privileges.sql
schemainspect/pg/sql/relations.sql
schemainspect/pg/sql/relations9.sql
schemainspect/pg/sql/rlspolicies.sql
schemainspect/pg/sql/roles.sql
schemainspect/pg/sql/schema-privileges.sql
schemainspect/pg/sql/schemas.sql
schemainspect/pg/sql/sequence-privileges.sql
schemainspect/pg/sql/sequences.sql
schemainspect/pg/sql/triggers.sql
schemainspect/pg/sql/types.sql
schemahq_schemainspect-1.0.12.dist-info/LICENSE
schemahq_schemainspect-1.0.12.dist-info/WHEEL
schemahq_schemainspect-1.0.12.dist-info/METADATA
schemahq_schemainspect-1.0.12.dist-info/RECORD
