Metadata-Version: 2.1
Name: schemahq-schemainspect
Version: 1.0.12
Summary: Schema inspection for PostgreSQL (and possibly others)
Home-page: https://github.com/djrobstep/schemainspect
License: Unlicense
Author: Robert Lechte
Author-email: robertlechte@gmail.com
Classifier: License :: Other/Proprietary License
Classifier: Programming Language :: Python :: 2
Classifier: Programming Language :: Python :: 2.7
Classifier: Programming Language :: Python :: 3
Classifier: Programming Language :: Python :: 3.4
Classifier: Programming Language :: Python :: 3.5
Classifier: Programming Language :: Python :: 3.6
Classifier: Programming Language :: Python :: 3.7
Classifier: Programming Language :: Python :: 3.8
Requires-Dist: six
Requires-Dist: sqlalchemy
Project-URL: Repository, https://github.com/djrobstep/schemainspect
